<?xml version="1.0" encoding="UTF-8"?>
<beans xmlns="http://www.springframework.org/schema/beans"
	xmlns:xsi="http://www.w3.org/2001/XMLSchema-instance" xmlns:p="http://www.springframework.org/schema/p"
	xmlns:tx="http://www.springframework.org/schema/tx" xmlns:aop="http://www.springframework.org/schema/aop"
	xmlns:context="http://www.springframework.org/schema/context"
	xmlns:task="http://www.springframework.org/schema/task"
	xsi:schemaLocation="http://www.springframework.org/schema/beans  
	http://www.springframework.org/schema/beans/spring-beans-3.0.xsd  
	http://www.springframework.org/schema/tx  
	http://www.springframework.org/schema/tx/spring-tx-3.0.xsd  
	http://www.springframework.org/schema/aop  
	http://www.springframework.org/schema/aop/spring-aop-3.0.xsd  
	http://www.springframework.org/schema/context  
	http://www.springframework.org/schema/context/spring-context-2.5.xsd
	http://www.springframework.org/schema/batch
    http://www.springframework.org/schema/batch/spring-batch-2.2.xsd
 	http://www.springframework.org/schema/task 
    http://www.springframework.org/schema/task/spring-task-3.0.xsd"
	default-autowire="byName">
	<!-- 任务注册器 -->
	<bean id="jobRegistry"
		class="org.springframework.batch.core.configuration.support.MapJobRegistry"></bean>
	 <bean
	    class="org.springframework.batch.core.configuration.support.JobRegistryBeanPostProcessor">
		<property name="jobRegistry" ref="jobRegistry" />
	</bean>	
		
	<!-- 作业仓库，任何任务的操作都会记录在作业仓库中，作业仓库有两种，内存和数据库 -->
	<bean id="jobRepository"
		class="org.springframework.batch.core.repository.support.MapJobRepositoryFactoryBean">

	</bean>
	<!-- 作业调度器，用来启动job -->
	<bean id="jobLauncher"
		class="org.springframework.batch.core.launch.support.SimpleJobLauncher">
		<property name="jobRepository" ref="jobRepository"></property>
	</bean>

	<!-- 异步作业调度器 -->
	<task:executor id="executor" pool-size="1" />
	<bean id="jobLauncherAsyn"
		class="org.springframework.batch.core.launch.support.SimpleJobLauncher">
		<property name="jobRepository" ref="jobRepository" />
		<property name="taskExecutor" ref="executor" />
	</bean>

	<!-- 定义事务管理器 -->
	<bean id="transactionManager"
		class="org.springframework.batch.support.transaction.ResourcelessTransactionManager">

	</bean>

</beans>
	